optimization_algorithms/__init__.py
optimization_algorithms/for_partitioning/__init__.py
optimization_algorithms/for_partitioning/hybridization_SA_KL_0103.py
optimization_algorithms/for_partitioning/kernighan_lin_0101.py
optimization_algorithms/for_partitioning/simulated_annealing_0102.py
optimization_algorithms-0.0.1.dist-info/LICENSE
optimization_algorithms-0.0.1.dist-info/METADATA
optimization_algorithms-0.0.1.dist-info/WHEEL
optimization_algorithms-0.0.1.dist-info/top_level.txt
optimization_algorithms-0.0.1.dist-info/RECORD
