Metadata-Version: 2.1
Name: optimization-algorithms
Version: 0.0.1
Summary: It is a Python library that contains useful algorithms for several complex problems such as partitioning, floor planning, scheduling.
Home-page: https://github.com/alqmase/optimization-algorithms
Author: Mohammed Alqmase
Author-email: alqumasi@gmail.com
License: UNKNOWN
Project-URL: Bug Tracker, https://github.com/alqmase/optimization-algorithms/issues
Platform: UNKNOWN
Classifier: Programming Language :: Python :: 3
Classifier: License :: OSI Approved :: MIT License
Classifier: Operating System :: OS Independent
Requires-Python: >=3.7
License-File: LICENSE
